docs/conf.py
examples/anatomical_diagram-nephron-Example.py
examples/decision_tree-NTA-Example.py
examples/example_arrows.py
examples/information_flow-calculus-Example.py
examples/plotting-blackbody_radiation-Example.py
logictree/__init__.py
logictree/arrow_etc.py
logictree/logicbox.py
logictree/logictree.py
logictree/vector_detector.py
logictree/fonts/Leelawadee.ttf
logictree/fonts/Times New Roman Italic.ttf
logictree/fonts/Times New Roman Regular.ttf
logictreeetc-0.1.2.dist-info/licenses/LICENSE
tests/test_arrow_etc.py
tests/test_logic_box.py
tests/test_logic_tree.py
tests/test_vector_detector.py
logictreeetc-0.1.2.dist-info/METADATA
logictreeetc-0.1.2.dist-info/WHEEL
logictreeetc-0.1.2.dist-info/top_level.txt
logictreeetc-0.1.2.dist-info/RECORD
